{
  "Google": "7c94bca23e8a841d60b36e79a1e6af2d",
  "Amazon": "a8050fc0cdf7d6e35b0d2e0d0d549c08",
  "Apple": "bbe3c2b720acf2ab8aad85a593b8477b",
  "LinkedIn": "6acf5a94f7b44e29c5b4a31e8622e769",
  "Qualcomm": "39f17ad06770cfe3dbefa56cd776dada",
  "Oracle": "30162ed78b6c10f731411f2fc440c24f",
  "Cisco": "41f1b5cdbcad2b67463887a3c352c1f1",
  "Texas Instruments": "80293b4ff94467c0484a58bc2894e211",
  "IBM": "08e51aa86172ec749f0d9ebb5239e0c4",
  "SAP": "6854ba398daab384713c1d0613b93318",
  "Stripe": [
    "https://stripe.com/jobs/search?gh_jid=6814190|||Product Support Operations Associate, Weekend Shift |||Bengaluru",
    "https://stripe.com/jobs/search?gh_jid=5423044|||Risk Operations Associate |||Bengaluru",
    "https://stripe.com/jobs/search?gh_jid=7577341|||EDD Quality Associate|||IN-Bengaluru",
    "https://stripe.com/jobs/search?gh_jid=7540835|||Operations Associate, Sanctions (FinCrime)|||Bengaluru",
    "https://stripe.com/jobs/search?gh_jid=7543868|||Software Engineer, Internal Systems|||Bengaluru, India",
    "https://stripe.com/jobs/search?gh_jid=7584867|||Marketing Content Operations Associate|||Bangalore",
    "https://stripe.com/jobs/search?gh_jid=7780256|||Operations Associate, GTM Accelerate (Bangalore)|||Bengaluru",
    "https://stripe.com/jobs/search?gh_jid=7179634|||Bridge - Operations Associate |||Bengaluru",
    "https://stripe.com/jobs/search?gh_jid=7573680|||Marketing Operations Associate (Automation)|||Bengaluru, India",
    "https://stripe.com/jobs/search?gh_jid=7236933|||Operations Associate, Apprenticeship|||Bengaluru",
    "https://stripe.com/jobs/search?gh_jid=7775311|||Recruitment Coordinator - People Operations Associate|||IN-Bengaluru",
    "https://stripe.com/jobs/search?gh_jid=7738241|||Verifications Operations Associate|||Bengaluru",
    "https://stripe.com/jobs/search?gh_jid=7748617|||Bridge Operations Associate |||Bengaluru "
  ],
  "Twilio": [
    "https://job-boards.greenhouse.io/twilio/jobs/7748964|||Video Producer Intern|||Remote - US",
    "https://job-boards.greenhouse.io/twilio/jobs/7728949|||Social Impact and Community Engagement Intern|||Remote - US",
    "https://job-boards.greenhouse.io/twilio/jobs/7748959|||Analyst Relations Intern|||Remote - US",
    "https://job-boards.greenhouse.io/twilio/jobs/7744133|||Public Relations & Social Media Intern|||Remote - US",
    "https://job-boards.greenhouse.io/twilio/jobs/7748961|||Technical Video Content Intern, Developer Ecosystem|||Remote - US",
    "https://job-boards.greenhouse.io/twilio/jobs/7585589|||Software Engineer Intern (June start, Remote-Ireland)|||Remote - Ireland",
    "https://job-boards.greenhouse.io/twilio/jobs/7728956|||Evangelist Intern|||Remote - US"
  ],
  "GitLab": [
    "https://job-boards.greenhouse.io/gitlab/jobs/8463951002|||Intermediate Backend Engineer, Gitlab Delivery: Upgrades|||Remote, India"
  ],
  "Rubrik": [
    "https://www.rubrik.com/company/careers/departments/job.7765355?gh_jid=7765355|||Product Management Intern|||Bangalore",
    "https://www.rubrik.com/company/careers/departments/job.7714998?gh_jid=7714998|||Legal Associate|||Bangalore",
    "https://www.rubrik.com/company/careers/departments/job.7770714?gh_jid=7770714|||Product Management Intern|||Bangalore"
  ],
  "Groww": [
    "https://job-boards.eu.greenhouse.io/groww/jobs/4771440101|||Video Editor Intern|||Bengaluru-VTP, India",
    "https://job-boards.eu.greenhouse.io/groww/jobs/4774341101|||Copy Writer - Intern|||Bengaluru-VTP, India",
    "https://job-boards.eu.greenhouse.io/groww/jobs/4771441101|||Intern - Finance Content Writer|||Bengaluru-VTP, India",
    "https://job-boards.eu.greenhouse.io/groww/jobs/4774342101|||Graphic Designer - Intern|||Bengaluru-VTP, India"
  ],
  "Dropbox": [
    "https://jobs.dropbox.com/listing/7309198?gh_jid=7309198|||Poland Software Engineering Intern (Summer 2026)|||Remote - Poland"
  ],
  "Flipkart": "e0110aede436639da1a6793ed1b69baf",
  "Zomato": "00fb567af6fb68978cd3fb1c79875239",
  "Swiggy": "974138ff04257f5b1e95e09145b83486",
  "Myntra": "c2d7f6cae2766d633664b0fd2eeed874",
  "BigBasket": "f258eb54855179e02e2d6c41fd106b10",
  "Cars24": "2057546c0c605f6bd94bebeabf14d0a9",
  "Paytm": "e50349c8427b8763f3299abd74544d6e",
  "PhonePe": "cd3fd91db74ba54373b75f91a2f949ae",
  "Zerodha": "dd58ca098f2d2e0fedb034b441ae4464",
  "Angel One": "2535bf5a1a0f99e5dcb46f3dc7b57b12",
  "BharatPe": "26b03fe9c306c770f1f037ddb09c0cc8",
  "Fi Money": "8e210e83784a733ac7c2546df12f0f33",
  "Goldman Sachs": "e26117f9e58c5981179c2eb651c6133d",
  "JP Morgan": "314ad7c17453165884b793ab8de65006",
  "BlackRock": "dd6fb8dad6f3a24a36598df3030b821e",
  "Axis Bank": "a9f6351baa4939014429ee0ec2274838",
  "HDFC Bank": "b2b2504b955f0e288a1c5211f2735b7f",
  "Snowflake": "7217a2d9961a8f5fbaf658d0a3295e49",
  "Accenture": "ab57211fd57759a6cb9fc218bb1335a9",
  "Capgemini": "78bf40202540c7b1d324259a699fb021",
  "Deloitte": "6926a1c0f1f12e2d361dd17f25c01b02",
  "BCG": "8f12775d0af21cb26ad5b4ee0c6413b8",
  "Bain & Company": "1fe585342b3c033a39c051a78c57367a",
  "EY": "7f92efbbfd4796d8b4c99d14847fd71e",
  "PwC": "91462c96c3e68910855ff6154a158616",
  "KPMG": "5011649334dfcedc4b476fc767bacfc1",
  "ThoughtWorks": "514c64798d630ef4615fd544fd4bc7ac",
  "ARM": "6e825b921e1660df9d869caebe236979",
  "Unacademy": "0ecc695136eb5801b511c39203e90933",
  "Tata 1mg": "7250578cb652bc4c28503267e28ca73f",
  "Cult.fit": "ee7ee942fdd3c951680ae061ac0b33c2",
  "Delhivery": "9dafe7857ece592567ef8bd9994118c8",
  "Dream11": "22dd96a6ac66b7250a534425b6a83bef",
  "Zoho": "82fd57059abf03dfee9506b2bbe39095",
  "Darwinbox": "781a39a2dc14be54a1d74239811dd43b",
  "HotStar": "05b9efdedd628736d68e759121a2ae9f",
  "Intuit": "c312caebd80aee7ae06ab995123a8836",
  "PayPal": "ede4c36e4246cfc420956d3939027510",
  "Mastercard": "52dca1b384173a4bb21a89ab7f42039e",
  "American Express": "e1f531565d6f0ff619e241e460a8c608",
  "Expedia": "f4fde6186f0edb2230c0a867ae40b673",
  "Walmart Global Tech": "21e6967ed3ba2f5528002a297d1bb8ce",
  "Palo Alto Networks": "264e6531122d0014e7b90cb733cdd0c4",
  "Zscaler": [
    "https://job-boards.greenhouse.io/zscaler/jobs/5046050007|||Site Reliability Engineer Federal- SkillBridge Intern|||Remote - Virginia, USA",
    "https://job-boards.greenhouse.io/zscaler/jobs/5045817007|||Site Reliability Engineer-SkillBridge Intern|||Remote - USA",
    "https://job-boards.greenhouse.io/zscaler/jobs/5069684007|||Federal Security Operations - SkillBridge Intern|||Remote - USA",
    "https://job-boards.greenhouse.io/zscaler/jobs/5100618007|||Insider Risk Analyst - SkillBridge Intern|||Remote - USA",
    "https://job-boards.greenhouse.io/zscaler/jobs/5020707007|||Associate Data Engineer|||Bangalore, IND; Mohali, IND; Pune, IND"
  ],
  "Pure Storage": [
    "https://job-boards.greenhouse.io/purestorage/jobs/7689246|||Associate Value Consultant|||Remote, North Carolina"
  ],
  "GlobalLogic": "e4e999164191746dd27749feea501bf5",
  "Persistent Systems": "4c6a222a25cd18cdeccdeffc7bb74743",
  "Mphasis": "31a6f2b68fa0fecae2b5736507467e1e",
  "Lam Research": "6abb737abda9df3de23c82f7aef386e1",
  "Applied Materials": "338c843e0ab1747adf3532808a356a09",
  "Societe Generale": "aaedb3780c9c483a5cf87708be92f8a0",
  "BNY Mellon": "45cd7198daf76813dfd89926ed16c351",
  "Optum UHG": "071f6b50e6608ed3bdf83697da17d8c1",
  "Siemens": "b16bc8624a9d0d256be946ffb41c1498",
  "Bosch India": "c136c692f6b244c303216ec7803717c2",
  "Honeywell": "3bfec49da4426d722ae050da25a87a7e",
  "Porter": "3eb0b842dac86f1ab655c56924ad3b47",
  "NoBroker": "2f267ab53f697a285d221ceb4d2a9b0b",
  "Niyo": "c23bfbc4e28f3ccc47af6236fd13a45c",
  "Vedantu": "29a2a75e8b720235c22d619228dd19e1",
  "Dailyhunt": "a87ab73c9434af7ad9debf7782b34598",
  "Analytics Vidhya": "a548ab10e5ee3543207dbafa3ed9c5f9",
  "Commvault": [
    "https://job-boards.greenhouse.io/commvault/jobs/5169041008|||Technical Specialist - SaaS Associate|||Bangalore, India"
  ],
  "Nagarro": "917319f15ad30aa60214ad6d872b1ba0",
  "Healthifyme": "49f9a924dc886d9979d43501a6e8ee5e",
  "Charles Schwab": "52a6fc95a62d7ee4dbbf60cdbb78be92",
  "Cyient": "69b23446daf1a5ecb747e11a9f0ece3d",
  "ABB": "112bec6b1cc7f7c38dc58e58d2430e52",
  "D. E. Shaw": "377558104cda1a75b1b4c20b1fadeb89",
  "Tower Research": "3a97fae188c8d2aeee1b38a3235aa1fd",
  "Arcesium": "003a0f406cc44421fe6245af13b5a627",
  "Splunk": "7f480a4985b658a6cd28da9efb1a6c4f",
  "Zeta": "f0c69048f0bcb0c1818a9df9e58195e3",
  "Grab": "ae3975715ff5f467cf66891821b4d7d6",
  "Coinbase": [
    "https://www.coinbase.com/careers/positions/7683744?gh_jid=7683744|||Internal Audit Analyst|||Remote - USA",
    "https://www.coinbase.com/careers/positions/7647593?gh_jid=7647593|||Trade Surveillance Associate|||Remote - USA",
    "https://www.coinbase.com/careers/positions/7670186?gh_jid=7670186|||International Communications Associate|||Remote - Australia",
    "https://www.coinbase.com/careers/positions/7707575?gh_jid=7707575|||Special Investigations Associate|||Remote - Brazil",
    "https://www.coinbase.com/careers/positions/7647776?gh_jid=7647776|||Regulatory Compliance Associate|||Remote - Australia"
  ],
  "Juspay": "cd45ce56a634805d2fbc0239770c0cc4",
  "Instacart": [
    "https://instacart.careers/job/?gh_jid=7572155|||Sales Associate|||United States - Remote",
    "https://instacart.careers/job/?gh_jid=7558978|||Sales Associate - New York|||United States - Remote",
    "https://instacart.careers/job/?gh_jid=7560993|||Sales Associate - San Francisco/Los Angeles|||United States - Remote"
  ],
  "Affirm": [
    "https://job-boards.greenhouse.io/affirm/jobs/7647925003|||Software Engineering Apprentice, Full-Stack|||Remote US"
  ],
  "Block (Square)": "100de9c12348f455e15364dfc9d9b9df",
  "Wise": "5839e518e64001f760f51097b02b1ffe",
  "Monzo": "b6aef33be377c9ccbce9d8eb45145a51",
  "Monday.com": "6175df40f81e6f6e4d771bb37914dc57",
  "Smartsheet": "0c028e99862878a46e85a1497e32217f",
  "Delivery Hero": "4620b1c812d8093737e395326ed43c8f",
  "Zalando": "44e63dc2eef6f4b2046057262a13ee23",
  "Shopee": "5b2f7fd9a95053326487e0e1eccae7a5",
  "Chewy": "f55ed016bf20c5957c5f6353291d863b",
  "UpGrad": "f4db567aa8ecf0b391f5a688392d1d71",
  "Kayak": "692ab9c503d49f2af239178468499d51",
  "Teladoc": "e18e27cb42ef024e38a8a854587fc602",
  "Pharmeasy": "4d08cb94b968ae242091960e57080511",
  "AMD": "42a6108541826950e86530da1b42c690",
  "ASML": "cfe979a3f10e348db326e3f1454fcaae",
  "Fortinet": "b32026e021a2d1619b50ff358d58a936",
  "Check Point": "76816c7a1d9a1c09244e0858923e4450",
  "Auth0": "20c66ab6b3475492dac97977ab72f299",
  "EA": "b671aacc348d98fdfb54afcd007dc8b9",
  "Activision Blizzard": "2130d071d6ecccc57a50a457115aefeb",
  "Take-Two": "6e4db76427cb0e0edfb4712a1afa12f4",
  "Ubisoft": "ce232e981a1595b15f3e1ffa9b938e16",
  "Nintendo": "830d705d9eabaad2f168564e9b9933f9",
  "Sony Interactive": "70e9fc9e6f83d4a231cb36b5113f715a",
  "Epic Games": "db7471b7b57dbd1cb12e047b7edf4cd9",
  "Zynga": "7cdcbe3a4021443b081ffbe31abcd1be",
  "King": "97b6405648a92d2e83c280b5578a494a",
  "Bumble": "d19c161ce136dd19b581578d3d732b2c",
  "Dell": "c83d5d40dfb94256fc2e504f37eae59d",
  "HP": "c26f500acfcffd02ab21e0ee4253dcea",
  "HPE": "b9feec4ad62fd78a1f0f26813dc05ce3",
  "NetApp": "30125b1cf6945bc60bcec01a2dc24b95",
  "Juniper": "ff48fe2882e7f08516e4ad5f228f482f",
  "Lockheed Martin": "1d2beac8def432a1cee960d779c841e4",
  "Northrop Grumman": "18eb7ffe5e2541f7d83d3c12559c7594",
  "Raytheon": "037f5b45bb206a9ee115c2167716b26f",
  "Waymo": "1182d8ef2cfb03847741830144731169",
  "DuckDuckGo": "b5ce70e9b17f4d1e28d64e27c1898b39",
  "Flexport": [
    "https://boards.greenhouse.io/flexport/jobs/7609526?gh_jid=7609526|||Air Operations Associate, Gurgaon|||New Delhi, India",
    "https://boards.greenhouse.io/flexport/jobs/7577181?gh_jid=7577181|||Customs Associate|||Canada Remote",
    "https://boards.greenhouse.io/flexport/jobs/7609848?gh_jid=7609848|||Ocean Operations Associate, Mumbai|||Mumbai, India",
    "https://boards.greenhouse.io/flexport/jobs/7744100?gh_jid=7744100|||Customs Associate (Night + Weekend Shift)|||Canada Remote"
  ],
  "Sequoia Capital": "015d7db12a6669c6ac0e887ac9d7c1cf",
  "Fastly": [
    "https://www.fastly.com/about/jobs/apply?gh_jid=7775181|||Associate eLearning Developer|||Pune, India"
  ],
  "Qualtrics": "b32f697a0c81189af7c7ed3ace3a537f",
  "Slack": "bd08434be4943385b01ed176186ad02a",
  "Tableau": "657dfcd32b3e64770e16d829fd3f687e",
  "Klarna": "c98d96fee4369e212b51b410b879e167",
  "Meta": "465e0724516de0794117c9fb07f48ab0",
  "Elastic": [
    "https://jobs.elastic.co/jobs?gh_jid=7565091&gh_jid=7565091|||Lifecycle Marketing Associate|||Bangalore, India"
  ],
  "Bloomberg": "9abb756f63375616afa4f8a4c9b4659b",
  "Roblox": [
    "https://careers.roblox.com/jobs/7783533?gh_jid=7783533|||Product Support Specialist, International|||Gurugram, Haryana, India"
  ]
}